squiggle/__init__.py
squiggle/cli.py
squiggle/squiggle.py
squiggle-0.3.1.dist-info/METADATA
squiggle-0.3.1.dist-info/RECORD
squiggle-0.3.1.dist-info/WHEEL
squiggle-0.3.1.dist-info/entry_points.txt
squiggle-0.3.1.dist-info/top_level.txt
